{
    "sceneQuestions": [
      {
        "sceneName": "CityBridge",
        "question": "Which polygon has the same shape as the label? Press the right hand joystick to confirm.",
        "mask": "Test",
        "answers": [
          "UserTesting/Answers/Hex1",
          "UserTesting/Answers/Hex2",
          "UserTesting/Answers/Hex3",
          "UserTesting/Answers/HexTrue_HotelParanal"
        ]
      },
      {
        "sceneName": "HotelParanal",
        "question": "Which polygon has the same shape as the label? Press the right hand joystick to confirm.",
        "mask": "HotelParanal_Test2",
        "answers": [
          "UserTesting/Answers/Hex1",
          "UserTesting/Answers/Hex3",
          "UserTesting/Answers/HexTrue_HotelParanal",
          "UserTesting/Answers/Hex2"
        ]
      },
      {
        "sceneName": "LaSilla",
        "question": "Which polygon has the same shape as the label? Press the right hand joystick to confirm.",
        "mask": "Test",
        "answers": [
          "UserTesting/Answers/HexTrue_HotelParanal",
          "UserTesting/Answers/Hex1",
          "UserTesting/Answers/Hex2",
          "UserTesting/Answers/Hex3"
        ]
      },
      {
        "sceneName": "LaSilla",
        "question": "Choose the labelling mode that optimizes visibility.",
        "mask": "Test",
        "answers": []
      }
    ]
  }